zettels/__init__.py
zettels/zettelkasten.py
zettels/zettelparser.py
zettels/zettels.py
zettels/zettels_setup.py
zettels/examples/index.yaml
zettels/examples/zettels.cfg.yaml
zettels/examples/Zettelkasten/file1.md
zettels/examples/Zettelkasten/file2.md
zettels/examples/Zettelkasten/file3.md
zettels/examples/Zettelkasten/onlies/markdown-only.md
zettels/examples/Zettelkasten/onlies/yaml-test.md
zettels/examples/Zettelkasten/subdir/file4.md
zettels/examples/Zettelkasten/subdir/file5.md
zettels/resources/zettels-grep-patterns
zettels-0.7.0.dist-info/DESCRIPTION.rst
zettels-0.7.0.dist-info/METADATA
zettels-0.7.0.dist-info/RECORD
zettels-0.7.0.dist-info/WHEEL
zettels-0.7.0.dist-info/entry_points.txt
zettels-0.7.0.dist-info/metadata.json
zettels-0.7.0.dist-info/top_level.txt
