Metadata-Version: 2.0
Name: zettels
Version: 0.7.0
Summary: A command line tool implementing Luhmann's system of a "Zettelkasten".
Home-page: https://github.com/sthesing/Zettels
Author: Stefan Thesing
Author-email: software@webdings.de
License: GPLv3+
Keywords: notetaking zettelkasten
Platform: UNKNOWN
Classifier: Development Status :: 3 - Alpha
Classifier: Intended Audience :: Science/Research
Classifier: Intended Audience :: Education
Classifier: Topic :: Text Processing :: Indexing
Classifier: Topic :: Other/Nonlisted Topic
Classifier: License :: OSI Approved :: GNU General Public License v3 or later (GPLv3+)
Classifier: Programming Language :: Python :: 3
Classifier: Programming Language :: Python :: 3.3
Classifier: Programming Language :: Python :: 3.4
Classifier: Programming Language :: Python :: 3.5
Provides-Extra: dev
Provides-Extra: test
Requires-Dist: PyYAML
Requires-Dist: pathspec (>=0.5.0)
Provides-Extra: dev
Requires-Dist: check-manifest; extra == 'dev'
Requires-Dist: pypandoc; extra == 'dev'
Provides-Extra: test
Requires-Dist: coverage; extra == 'test'
